<?xml version = '1.0' encoding = 'UTF-8'?>
<j2ee:java-wsdl-mapping xmlns:j2ee="http://java.sun.com/xml/ns/j2ee" xmlns:xsi="http://www.w3.org/2001/XMLSchema-instance" version="1.1">
  <j2ee:package-mapping>
    <j2ee:package-type>be.e1.bssv.J560201.proxy</j2ee:package-type>
    <j2ee:namespaceURI>http://xmlns.oracle.com/ApprovalGatewayManager/ApprovalGateway/ProcessApprovalGateway</j2ee:namespaceURI>
  </j2ee:package-mapping>
  <j2ee:package-mapping>
    <j2ee:package-type>be.e1.bssv.J560201.com.beaerospace.approvalgateway</j2ee:package-type>
    <j2ee:namespaceURI>http://www.beaerospace.com/ApprovalGateway</j2ee:namespaceURI>
  </j2ee:package-mapping>
  <j2ee:java-xml-type-mapping>
    <j2ee:java-type>be.e1.bssv.J560201.com.beaerospace.approvalgateway.ApprovalGatewayRequest</j2ee:java-type>
    <j2ee:root-type-qname xmlns:app="http://www.beaerospace.com/ApprovalGateway">app:ApprovalGatewayRequest</j2ee:root-type-qname>
    <j2ee:qname-scope>element</j2ee:qname-scope>
  </j2ee:java-xml-type-mapping>
  <j2ee:java-xml-type-mapping>
    <j2ee:java-type>be.e1.bssv.J560201.com.beaerospace.approvalgateway.ApprovalGatewayReply</j2ee:java-type>
    <j2ee:root-type-qname xmlns:app="http://www.beaerospace.com/ApprovalGateway">app:ApprovalGatewayReply</j2ee:root-type-qname>
    <j2ee:qname-scope>element</j2ee:qname-scope>
  </j2ee:java-xml-type-mapping>
  <j2ee:java-xml-type-mapping>
    <j2ee:java-type>be.e1.bssv.J560201.com.beaerospace.approvalgateway.ApprovalGatewayRequest</j2ee:java-type>
    <j2ee:anonymous-type-qname>http://www.beaerospace.com/ApprovalGateway:>ApprovalGatewayRequest</j2ee:anonymous-type-qname>
    <j2ee:qname-scope>complexType</j2ee:qname-scope>
    <j2ee:variable-mapping>
      <j2ee:java-variable-name>MessageId</j2ee:java-variable-name>
      <j2ee:xml-element-name>MessageId</j2ee:xml-element-name>
    </j2ee:variable-mapping>
    <j2ee:variable-mapping>
      <j2ee:java-variable-name>ProcessType</j2ee:java-variable-name>
      <j2ee:xml-element-name>ProcessType</j2ee:xml-element-name>
    </j2ee:variable-mapping>
    <j2ee:variable-mapping>
      <j2ee:java-variable-name>OriginalProcess</j2ee:java-variable-name>
      <j2ee:xml-element-name>OriginalProcess</j2ee:xml-element-name>
    </j2ee:variable-mapping>
    <j2ee:variable-mapping>
      <j2ee:java-variable-name>ProcessPayload</j2ee:java-variable-name>
      <j2ee:xml-element-name>ProcessPayload</j2ee:xml-element-name>
    </j2ee:variable-mapping>
  </j2ee:java-xml-type-mapping>
  <j2ee:java-xml-type-mapping>
    <j2ee:java-type>be.e1.bssv.J560201.com.beaerospace.approvalgateway.ApprovalGatewayReply</j2ee:java-type>
    <j2ee:anonymous-type-qname>http://www.beaerospace.com/ApprovalGateway:>ApprovalGatewayReply</j2ee:anonymous-type-qname>
    <j2ee:qname-scope>complexType</j2ee:qname-scope>
    <j2ee:variable-mapping>
      <j2ee:java-variable-name>Status</j2ee:java-variable-name>
      <j2ee:xml-element-name>Status</j2ee:xml-element-name>
    </j2ee:variable-mapping>
    <j2ee:variable-mapping>
      <j2ee:java-variable-name>Message</j2ee:java-variable-name>
      <j2ee:xml-element-name>Message</j2ee:xml-element-name>
    </j2ee:variable-mapping>
    <j2ee:variable-mapping>
      <j2ee:java-variable-name>InstanceId</j2ee:java-variable-name>
      <j2ee:xml-element-name>InstanceId</j2ee:xml-element-name>
    </j2ee:variable-mapping>
  </j2ee:java-xml-type-mapping>
  <j2ee:service-interface-mapping>
    <j2ee:service-interface>be.e1.bssv.J560201.proxy.Processapprovalgateway_Client_Ep</j2ee:service-interface>
    <j2ee:wsdl-service-name xmlns:proc="http://xmlns.oracle.com/ApprovalGatewayManager/ApprovalGateway/ProcessApprovalGateway">proc:processapprovalgateway_client_ep</j2ee:wsdl-service-name>
    <j2ee:port-mapping>
      <j2ee:port-name>ProcessApprovalGateway_pt</j2ee:port-name>
      <j2ee:java-port-name>ProcessApprovalGateway_Pt</j2ee:java-port-name>
    </j2ee:port-mapping>
  </j2ee:service-interface-mapping>
  <j2ee:service-endpoint-interface-mapping>
    <j2ee:service-endpoint-interface>be.e1.bssv.J560201.proxy.ProcessApprovalGateway</j2ee:service-endpoint-interface>
    <j2ee:wsdl-port-type xmlns:proc="http://xmlns.oracle.com/ApprovalGatewayManager/ApprovalGateway/ProcessApprovalGateway">proc:ProcessApprovalGateway</j2ee:wsdl-port-type>
    <j2ee:wsdl-binding xmlns:proc="http://xmlns.oracle.com/ApprovalGatewayManager/ApprovalGateway/ProcessApprovalGateway">proc:ProcessApprovalGatewayBinding</j2ee:wsdl-binding>
    <j2ee:service-endpoint-method-mapping>
      <j2ee:java-method-name>process</j2ee:java-method-name>
      <j2ee:wsdl-operation>process</j2ee:wsdl-operation>
      <j2ee:method-param-parts-mapping>
        <j2ee:param-position>0</j2ee:param-position>
        <j2ee:param-type>be.e1.bssv.J560201.com.beaerospace.approvalgateway.ApprovalGatewayRequest</j2ee:param-type>
        <j2ee:wsdl-message-mapping>
          <j2ee:wsdl-message xmlns:proc="http://xmlns.oracle.com/ApprovalGatewayManager/ApprovalGateway/ProcessApprovalGateway">proc:ProcessApprovalGatewayRequestMessage</j2ee:wsdl-message>
          <j2ee:wsdl-message-part-name>payload</j2ee:wsdl-message-part-name>
          <j2ee:parameter-mode>IN</j2ee:parameter-mode>
        </j2ee:wsdl-message-mapping>
      </j2ee:method-param-parts-mapping>
      <j2ee:wsdl-return-value-mapping>
        <j2ee:method-return-value>be.e1.bssv.J560201.com.beaerospace.approvalgateway.ApprovalGatewayReply</j2ee:method-return-value>
        <j2ee:wsdl-message xmlns:proc="http://xmlns.oracle.com/ApprovalGatewayManager/ApprovalGateway/ProcessApprovalGateway">proc:ProcessApprovalGatewayResponseMessage</j2ee:wsdl-message>
        <j2ee:wsdl-message-part-name>payload</j2ee:wsdl-message-part-name>
      </j2ee:wsdl-return-value-mapping>
    </j2ee:service-endpoint-method-mapping>
  </j2ee:service-endpoint-interface-mapping>
</j2ee:java-wsdl-mapping>
